{
  "schema_version": 2,
  "id": "justjavac/proton-path",
  "version": "0.1.10",
  "display_name": "Path",
  "description": "Portable path helpers exposed through a JavaScript-friendly namespace.",
  "namespace": "path",
  "package": "justjavac/proton_ext/path",
  "spec_symbol": "extension",
  "manifest_key": "justjavac/proton-path",
  "platforms": ["windows", "macos", "linux"],
  "dependencies": [],
  "capabilities": ["path.resolve", "path.join", "path.parse", "path.relative"],
  "permissions": [],
  "risk_level": "low",
  "options_schema": "./options.schema.json"
}
